rklibpy/__init__.py
rklibpy/address.py
rklibpy/assets.py
rklibpy/block.py
rklibpy/blockchain.py
rklibpy/permissions.py
rklibpy/stream.py
rklibpy/transaction.py
rklibpy/wallet.py
rklibpy/test/__init__.py
rklibpy/test/test_address.py
rklibpy/test/test_assets.py
rklibpy/test/test_block.py
rklibpy/test/test_blockchain.py
rklibpy/test/test_permissions.py
rklibpy/test/test_stream.py
rklibpy/test/test_transaction.py
rklibpy/test/test_wallet.py
rklibpy-0.1.0.dist-info/DESCRIPTION.rst
rklibpy-0.1.0.dist-info/METADATA
rklibpy-0.1.0.dist-info/RECORD
rklibpy-0.1.0.dist-info/WHEEL
rklibpy-0.1.0.dist-info/metadata.json
rklibpy-0.1.0.dist-info/top_level.txt
