Metadata-Version: 2.0
Name: rklibpy
Version: 0.1.0
Summary: RecordsKeeper Python library
Home-page: https://github.com/RecordsKeeper/recordskeeper-python-sdk
Author: UNKNOWN
Author-email: UNKNOWN
License: UNKNOWN
Keywords: recordskeeper
Platform: UNKNOWN
Classifier: Programming Language :: Python
Requires-Dist: requests
Requires-Dist: green
Requires-Dist: pyyaml
